{
	"assets": [
		{
			"name": "Mini Mole Fresnel",
			"description": null,
			"price": "31.95",
			"identifier": "MMF003",
			"vendor_id": null,
			"group_id": 102133,
			"created_at": "2023-07-18 15:32:29",
			"updated_at": "2023-11-14 11:38:45",
			"checkin_due_on": null,
			"audit_pending": false,
			"sequence_num": 728,
			"product_model_number": null,
			"documents_count": 0,
			"services_count": 0,
			"comments_count": 1,
			"state": "available",
			"purchased_on": null,
			"retired_on": null,
			"location_id": 12371,
			"net_quantity": 1,
			"pending_verification": false,
			"salvage_value": "0.0",
			"package_id": null,
			"checkout_on": null,
			"inventory_threshold": 0,
			"retire_reason": null,
			"retire_comments": null,
			"sub_group_id": null,
			"location_based_threshold": 0,
			"arbitration": 2,
			"rent_collected": "15.0",
			"tax_free": false,
			"sale_price": "0.0",
			"retired_by_id": null,
			"featured_item": false,
			"visible_on_web_store": false,
			"is_processed": false,
			"rental_meter": 0,
			"rental_meter_threshold": 0,
			"initial_stock_quantity": 0,
			"quickbooks_item_id": null,
			"sub_checked_out_to_id": null,
			"advanced_pricing": false,
			"bulk_import_id": null,
			"purchase_order_id": null,
			"available_for_sale": false,
			"checkout_via_bundle": false,
			"clone_from_asset_id": 2898417,
			"itam_hardware_id": null,
			"created_by_itam": false,
			"hidden_on_web_store": false,
			"last_checked_out_at": "2023-11-06 10:22:47",
			"last_checked_in_at": null,
			"last_assigned_to_id": 21718,
			"synced_with_jira_at": null,
			"sunshine_id": null,
			"retire_reason_id": null,
			"it_asset_source": null,
			"current_meter_reading": "0.0",
			"custom_substate_id": null,
			"merge_date": null,
			"candidate_email": null,
			"default_excess_location_threshold": 0,
			"average_cost_per_unit": "0.0",
			"usage_meter_threshold": null,
			"send_usage_meter_threshold_recurring_alert": false,
			"update_counter": 0,
			"network_asset": false,
			"group_rule_provisioned": false,
			"last_history_id": 9078458,
			"qbd_item_name": null,
			"item_audit_id": null,
			"product_id": 41058,
			"product_identity": "minimolefresnel",
			"external_asset": false,
			"holder_id": null,
			"depreciation_calculation_required": false,
			"location_rule_provisioned": false,
			"latest_contract_id": null,
			"manufacturer": null,
			"assigned_to_user_name": null,
			"asset_type": "FixedAsset",
			"sub_checked_out_to_full_name": null,
			"active_sub_checkout": null,
			"location_number": 1,
			"group": {
				"depreciation_rates": [
					{
						"id": 69696,
						"group_id": 102133,
						"depreciation_method_id": 149,
						"rate": "20.0",
						"created_at": "2022-03-05 22:11:22",
						"updated_at": "2022-03-05 22:11:22",
						"useful_life": 12,
						"depreciation_method_name": "Straight Line"
					}
				]
			},
			"primary_user": null,
			"assigned_to_user_email": null,
			"display_image": "/images/no-image.jpg",
			"location_name": "DFW",
			"depreciated_value": {
				"straight_line": "$31.95"
			},
			"action": "create",
			"rental_prices": {
				"per_minute": "0.0",
				"hourly": "0.0",
				"daily": "0.0",
				"weekly": "15.0",
				"monthly": "0.0"
			}
		},
		{
			"name": "Mini Mole Fresnel",
			"description": null,
			"price": "31.95",
			"identifier": "MMF004",
			"vendor_id": null,
			"group_id": 102133,
			"created_at": "2023-07-18 15:32:29",
			"updated_at": "2023-07-25 12:03:16",
			"checkin_due_on": null,
			"audit_pending": false,
			"sequence_num": 729,
			"product_model_number": null,
			"documents_count": 0,
			"services_count": 0,
			"comments_count": 1,
			"state": "available",
			"purchased_on": null,
			"retired_on": null,
			"location_id": 12371,
			"net_quantity": 1,
			"pending_verification": false,
			"salvage_value": "0.0",
			"package_id": null,
			"checkout_on": null,
			"inventory_threshold": 0,
			"retire_reason": null,
			"retire_comments": null,
			"sub_group_id": null,
			"location_based_threshold": 0,
			"arbitration": 2,
			"rent_collected": "0.0",
			"tax_free": false,
			"sale_price": "0.0",
			"retired_by_id": null,
			"featured_item": false,
			"visible_on_web_store": false,
			"is_processed": false,
			"rental_meter": 0,
			"rental_meter_threshold": 0,
			"initial_stock_quantity": 0,
			"quickbooks_item_id": null,
			"sub_checked_out_to_id": null,
			"advanced_pricing": false,
			"bulk_import_id": null,
			"purchase_order_id": null,
			"available_for_sale": false,
			"checkout_via_bundle": false,
			"clone_from_asset_id": 2898417,
			"itam_hardware_id": null,
			"created_by_itam": false,
			"hidden_on_web_store": false,
			"last_checked_out_at": null,
			"last_checked_in_at": null,
			"last_assigned_to_id": null,
			"synced_with_jira_at": null,
			"sunshine_id": null,
			"retire_reason_id": null,
			"it_asset_source": null,
			"current_meter_reading": "0.0",
			"custom_substate_id": null,
			"merge_date": null,
			"candidate_email": null,
			"default_excess_location_threshold": 0,
			"average_cost_per_unit": "0.0",
			"usage_meter_threshold": null,
			"send_usage_meter_threshold_recurring_alert": false,
			"update_counter": 0,
			"network_asset": false,
			"group_rule_provisioned": false,
			"last_history_id": null,
			"qbd_item_name": null,
			"item_audit_id": null,
			"product_id": 41058,
			"product_identity": "minimolefresnel",
			"external_asset": false,
			"holder_id": null,
			"depreciation_calculation_required": false,
			"location_rule_provisioned": false,
			"latest_contract_id": null,
			"manufacturer": null,
			"assigned_to_user_name": null,
			"asset_type": "FixedAsset",
			"sub_checked_out_to_full_name": null,
			"active_sub_checkout": null,
			"location_number": 1,
			"group": {
				"depreciation_rates": [
					{
						"id": 69696,
						"group_id": 102133,
						"depreciation_method_id": 149,
						"rate": "20.0",
						"created_at": "2022-03-05 22:11:22",
						"updated_at": "2022-03-05 22:11:22",
						"useful_life": 12,
						"depreciation_method_name": "Straight Line"
					}
				]
			},
			"primary_user": null,
			"assigned_to_user_email": null,
			"display_image": "/images/no-image.jpg",
			"location_name": "DFW",
			"depreciated_value": {
				"straight_line": "$31.95"
			},
			"action": "create",
			"rental_prices": {
				"per_minute": "0.0",
				"hourly": "0.0",
				"daily": "0.0",
				"weekly": "15.0",
				"monthly": "0.0"
			}
		},
		{
			"name": "Mini Mole Fresnel",
			"description": null,
			"price": "31.95",
			"identifier": "MMF005",
			"vendor_id": null,
			"group_id": 102133,
			"created_at": "2023-07-18 15:32:29",
			"updated_at": "2023-07-25 12:03:16",
			"checkin_due_on": null,
			"audit_pending": false,
			"sequence_num": 730,
			"product_model_number": null,
			"documents_count": 0,
			"services_count": 0,
			"comments_count": 1,
			"state": "available",
			"purchased_on": null,
			"retired_on": null,
			"location_id": 12371,
			"net_quantity": 1,
			"pending_verification": false,
			"salvage_value": "0.0",
			"package_id": null,
			"checkout_on": null,
			"inventory_threshold": 0,
			"retire_reason": null,
			"retire_comments": null,
			"sub_group_id": null,
			"location_based_threshold": 0,
			"arbitration": 2,
			"rent_collected": "0.0",
			"tax_free": false,
			"sale_price": "0.0",
			"retired_by_id": null,
			"featured_item": false,
			"visible_on_web_store": false,
			"is_processed": false,
			"rental_meter": 0,
			"rental_meter_threshold": 0,
			"initial_stock_quantity": 0,
			"quickbooks_item_id": null,
			"sub_checked_out_to_id": null,
			"advanced_pricing": false,
			"bulk_import_id": null,
			"purchase_order_id": null,
			"available_for_sale": false,
			"checkout_via_bundle": false,
			"clone_from_asset_id": 2898417,
			"itam_hardware_id": null,
			"created_by_itam": false,
			"hidden_on_web_store": false,
			"last_checked_out_at": null,
			"last_checked_in_at": null,
			"last_assigned_to_id": null,
			"synced_with_jira_at": null,
			"sunshine_id": null,
			"retire_reason_id": null,
			"it_asset_source": null,
			"current_meter_reading": "0.0",
			"custom_substate_id": null,
			"merge_date": null,
			"candidate_email": null,
			"default_excess_location_threshold": 0,
			"average_cost_per_unit": "0.0",
			"usage_meter_threshold": null,
			"send_usage_meter_threshold_recurring_alert": false,
			"update_counter": 0,
			"network_asset": false,
			"group_rule_provisioned": false,
			"last_history_id": null,
			"qbd_item_name": null,
			"item_audit_id": null,
			"product_id": 41058,
			"product_identity": "minimolefresnel",
			"external_asset": false,
			"holder_id": null,
			"depreciation_calculation_required": false,
			"location_rule_provisioned": false,
			"latest_contract_id": null,
			"manufacturer": null,
			"assigned_to_user_name": null,
			"asset_type": "FixedAsset",
			"sub_checked_out_to_full_name": null,
			"active_sub_checkout": null,
			"location_number": 1,
			"group": {
				"depreciation_rates": [
					{
						"id": 69696,
						"group_id": 102133,
						"depreciation_method_id": 149,
						"rate": "20.0",
						"created_at": "2022-03-05 22:11:22",
						"updated_at": "2022-03-05 22:11:22",
						"useful_life": 12,
						"depreciation_method_name": "Straight Line"
					}
				]
			},
			"primary_user": null,
			"assigned_to_user_email": null,
			"display_image": "/images/no-image.jpg",
			"location_name": "DFW",
			"depreciated_value": {
				"straight_line": "$31.95"
			},
			"action": "create",
			"rental_prices": {
				"per_minute": "0.0",
				"hourly": "0.0",
				"daily": "0.0",
				"weekly": "15.0",
				"monthly": "0.0"
			}
		},
		{
			"name": "Mini Mole Fresnel",
			"description": null,
			"price": "31.95",
			"identifier": "MMF006",
			"vendor_id": null,
			"group_id": 102133,
			"created_at": "2023-07-18 15:32:29",
			"updated_at": "2023-07-25 12:03:16",
			"checkin_due_on": null,
			"audit_pending": false,
			"sequence_num": 731,
			"product_model_number": null,
			"documents_count": 0,
			"services_count": 0,
			"comments_count": 1,
			"state": "available",
			"purchased_on": null,
			"retired_on": null,
			"location_id": 12371,
			"net_quantity": 1,
			"pending_verification": false,
			"salvage_value": "0.0",
			"package_id": null,
			"checkout_on": null,
			"inventory_threshold": 0,
			"retire_reason": null,
			"retire_comments": null,
			"sub_group_id": null,
			"location_based_threshold": 0,
			"arbitration": 2,
			"rent_collected": "0.0",
			"tax_free": false,
			"sale_price": "0.0",
			"retired_by_id": null,
			"featured_item": false,
			"visible_on_web_store": false,
			"is_processed": false,
			"rental_meter": 0,
			"rental_meter_threshold": 0,
			"initial_stock_quantity": 0,
			"quickbooks_item_id": null,
			"sub_checked_out_to_id": null,
			"advanced_pricing": false,
			"bulk_import_id": null,
			"purchase_order_id": null,
			"available_for_sale": false,
			"checkout_via_bundle": false,
			"clone_from_asset_id": 2898417,
			"itam_hardware_id": null,
			"created_by_itam": false,
			"hidden_on_web_store": false,
			"last_checked_out_at": null,
			"last_checked_in_at": null,
			"last_assigned_to_id": null,
			"synced_with_jira_at": null,
			"sunshine_id": null,
			"retire_reason_id": null,
			"it_asset_source": null,
			"current_meter_reading": "0.0",
			"custom_substate_id": null,
			"merge_date": null,
			"candidate_email": null,
			"default_excess_location_threshold": 0,
			"average_cost_per_unit": "0.0",
			"usage_meter_threshold": null,
			"send_usage_meter_threshold_recurring_alert": false,
			"update_counter": 0,
			"network_asset": false,
			"group_rule_provisioned": false,
			"last_history_id": null,
			"qbd_item_name": null,
			"item_audit_id": null,
			"product_id": 41058,
			"product_identity": "minimolefresnel",
			"external_asset": false,
			"holder_id": null,
			"depreciation_calculation_required": false,
			"location_rule_provisioned": false,
			"latest_contract_id": null,
			"manufacturer": null,
			"assigned_to_user_name": null,
			"asset_type": "FixedAsset",
			"sub_checked_out_to_full_name": null,
			"active_sub_checkout": null,
			"location_number": 1,
			"group": {
				"depreciation_rates": [
					{
						"id": 69696,
						"group_id": 102133,
						"depreciation_method_id": 149,
						"rate": "20.0",
						"created_at": "2022-03-05 22:11:22",
						"updated_at": "2022-03-05 22:11:22",
						"useful_life": 12,
						"depreciation_method_name": "Straight Line"
					}
				]
			},
			"primary_user": null,
			"assigned_to_user_email": null,
			"display_image": "/images/no-image.jpg",
			"location_name": "DFW",
			"depreciated_value": {
				"straight_line": "$31.95"
			},
			"action": "create",
			"rental_prices": {
				"per_minute": "0.0",
				"hourly": "0.0",
				"daily": "0.0",
				"weekly": "15.0",
				"monthly": "0.0"
			}
		},
		{
			"name": "Mini Mole Fresnel",
			"description": null,
			"price": "31.95",
			"identifier": "MMF007",
			"vendor_id": null,
			"group_id": 102133,
			"created_at": "2023-07-18 15:32:29",
			"updated_at": "2023-07-25 12:03:16",
			"checkin_due_on": null,
			"audit_pending": false,
			"sequence_num": 732,
			"product_model_number": null,
			"documents_count": 0,
			"services_count": 0,
			"comments_count": 1,
			"state": "available",
			"purchased_on": null,
			"retired_on": null,
			"location_id": 12371,
			"net_quantity": 1,
			"pending_verification": false,
			"salvage_value": "0.0",
			"package_id": null,
			"checkout_on": null,
			"inventory_threshold": 0,
			"retire_reason": null,
			"retire_comments": null,
			"sub_group_id": null,
			"location_based_threshold": 0,
			"arbitration": 2,
			"rent_collected": "0.0",
			"tax_free": false,
			"sale_price": "0.0",
			"retired_by_id": null,
			"featured_item": false,
			"visible_on_web_store": false,
			"is_processed": false,
			"rental_meter": 0,
			"rental_meter_threshold": 0,
			"initial_stock_quantity": 0,
			"quickbooks_item_id": null,
			"sub_checked_out_to_id": null,
			"advanced_pricing": false,
			"bulk_import_id": null,
			"purchase_order_id": null,
			"available_for_sale": false,
			"checkout_via_bundle": false,
			"clone_from_asset_id": 2898417,
			"itam_hardware_id": null,
			"created_by_itam": false,
			"hidden_on_web_store": false,
			"last_checked_out_at": null,
			"last_checked_in_at": null,
			"last_assigned_to_id": null,
			"synced_with_jira_at": null,
			"sunshine_id": null,
			"retire_reason_id": null,
			"it_asset_source": null,
			"current_meter_reading": "0.0",
			"custom_substate_id": null,
			"merge_date": null,
			"candidate_email": null,
			"default_excess_location_threshold": 0,
			"average_cost_per_unit": "0.0",
			"usage_meter_threshold": null,
			"send_usage_meter_threshold_recurring_alert": false,
			"update_counter": 0,
			"network_asset": false,
			"group_rule_provisioned": false,
			"last_history_id": null,
			"qbd_item_name": null,
			"item_audit_id": null,
			"product_id": 41058,
			"product_identity": "minimolefresnel",
			"external_asset": false,
			"holder_id": null,
			"depreciation_calculation_required": false,
			"location_rule_provisioned": false,
			"latest_contract_id": null,
			"manufacturer": null,
			"assigned_to_user_name": null,
			"asset_type": "FixedAsset",
			"sub_checked_out_to_full_name": null,
			"active_sub_checkout": null,
			"location_number": 1,
			"group": {
				"depreciation_rates": [
					{
						"id": 69696,
						"group_id": 102133,
						"depreciation_method_id": 149,
						"rate": "20.0",
						"created_at": "2022-03-05 22:11:22",
						"updated_at": "2022-03-05 22:11:22",
						"useful_life": 12,
						"depreciation_method_name": "Straight Line"
					}
				]
			},
			"primary_user": null,
			"assigned_to_user_email": null,
			"display_image": "/images/no-image.jpg",
			"location_name": "DFW",
			"depreciated_value": {
				"straight_line": "$31.95"
			},
			"action": "create",
			"rental_prices": {
				"per_minute": "0.0",
				"hourly": "0.0",
				"daily": "0.0",
				"weekly": "15.0",
				"monthly": "0.0"
			}
		},
		{
			"name": "Mini Mole Fresnel",
			"description": null,
			"price": "31.95",
			"identifier": "MMF008",
			"vendor_id": null,
			"group_id": 102133,
			"created_at": "2023-07-18 15:32:30",
			"updated_at": "2023-07-25 12:03:16",
			"checkin_due_on": null,
			"audit_pending": false,
			"sequence_num": 733,
			"product_model_number": null,
			"documents_count": 0,
			"services_count": 0,
			"comments_count": 1,
			"state": "available",
			"purchased_on": null,
			"retired_on": null,
			"location_id": 12371,
			"net_quantity": 1,
			"pending_verification": false,
			"salvage_value": "0.0",
			"package_id": null,
			"checkout_on": null,
			"inventory_threshold": 0,
			"retire_reason": null,
			"retire_comments": null,
			"sub_group_id": null,
			"location_based_threshold": 0,
			"arbitration": 2,
			"rent_collected": "0.0",
			"tax_free": false,
			"sale_price": "0.0",
			"retired_by_id": null,
			"featured_item": false,
			"visible_on_web_store": false,
			"is_processed": false,
			"rental_meter": 0,
			"rental_meter_threshold": 0,
			"initial_stock_quantity": 0,
			"quickbooks_item_id": null,
			"sub_checked_out_to_id": null,
			"advanced_pricing": false,
			"bulk_import_id": null,
			"purchase_order_id": null,
			"available_for_sale": false,
			"checkout_via_bundle": false,
			"clone_from_asset_id": 2898417,
			"itam_hardware_id": null,
			"created_by_itam": false,
			"hidden_on_web_store": false,
			"last_checked_out_at": null,
			"last_checked_in_at": null,
			"last_assigned_to_id": null,
			"synced_with_jira_at": null,
			"sunshine_id": null,
			"retire_reason_id": null,
			"it_asset_source": null,
			"current_meter_reading": "0.0",
			"custom_substate_id": null,
			"merge_date": null,
			"candidate_email": null,
			"default_excess_location_threshold": 0,
			"average_cost_per_unit": "0.0",
			"usage_meter_threshold": null,
			"send_usage_meter_threshold_recurring_alert": false,
			"update_counter": 0,
			"network_asset": false,
			"group_rule_provisioned": false,
			"last_history_id": null,
			"qbd_item_name": null,
			"item_audit_id": null,
			"product_id": 41058,
			"product_identity": "minimolefresnel",
			"external_asset": false,
			"holder_id": null,
			"depreciation_calculation_required": false,
			"location_rule_provisioned": false,
			"latest_contract_id": null,
			"manufacturer": null,
			"assigned_to_user_name": null,
			"asset_type": "FixedAsset",
			"sub_checked_out_to_full_name": null,
			"active_sub_checkout": null,
			"location_number": 1,
			"group": {
				"depreciation_rates": [
					{
						"id": 69696,
						"group_id": 102133,
						"depreciation_method_id": 149,
						"rate": "20.0",
						"created_at": "2022-03-05 22:11:22",
						"updated_at": "2022-03-05 22:11:22",
						"useful_life": 12,
						"depreciation_method_name": "Straight Line"
					}
				]
			},
			"primary_user": null,
			"assigned_to_user_email": null,
			"display_image": "/images/no-image.jpg",
			"location_name": "DFW",
			"depreciated_value": {
				"straight_line": "$31.95"
			},
			"action": "create",
			"rental_prices": {
				"per_minute": "0.0",
				"hourly": "0.0",
				"daily": "0.0",
				"weekly": "15.0",
				"monthly": "0.0"
			}
		},
		{
			"name": "Mini Mole Fresnel",
			"description": null,
			"price": "31.95",
			"identifier": "MMF009",
			"vendor_id": null,
			"group_id": 102133,
			"created_at": "2023-07-18 15:32:30",
			"updated_at": "2023-07-25 12:03:16",
			"checkin_due_on": null,
			"audit_pending": false,
			"sequence_num": 734,
			"product_model_number": null,
			"documents_count": 0,
			"services_count": 0,
			"comments_count": 1,
			"state": "available",
			"purchased_on": null,
			"retired_on": null,
			"location_id": 12371,
			"net_quantity": 1,
			"pending_verification": false,
			"salvage_value": "0.0",
			"package_id": null,
			"checkout_on": null,
			"inventory_threshold": 0,
			"retire_reason": null,
			"retire_comments": null,
			"sub_group_id": null,
			"location_based_threshold": 0,
			"arbitration": 2,
			"rent_collected": "0.0",
			"tax_free": false,
			"sale_price": "0.0",
			"retired_by_id": null,
			"featured_item": false,
			"visible_on_web_store": false,
			"is_processed": false,
			"rental_meter": 0,
			"rental_meter_threshold": 0,
			"initial_stock_quantity": 0,
			"quickbooks_item_id": null,
			"sub_checked_out_to_id": null,
			"advanced_pricing": false,
			"bulk_import_id": null,
			"purchase_order_id": null,
			"available_for_sale": false,
			"checkout_via_bundle": false,
			"clone_from_asset_id": 2898417,
			"itam_hardware_id": null,
			"created_by_itam": false,
			"hidden_on_web_store": false,
			"last_checked_out_at": null,
			"last_checked_in_at": null,
			"last_assigned_to_id": null,
			"synced_with_jira_at": null,
			"sunshine_id": null,
			"retire_reason_id": null,
			"it_asset_source": null,
			"current_meter_reading": "0.0",
			"custom_substate_id": null,
			"merge_date": null,
			"candidate_email": null,
			"default_excess_location_threshold": 0,
			"average_cost_per_unit": "0.0",
			"usage_meter_threshold": null,
			"send_usage_meter_threshold_recurring_alert": false,
			"update_counter": 0,
			"network_asset": false,
			"group_rule_provisioned": false,
			"last_history_id": null,
			"qbd_item_name": null,
			"item_audit_id": null,
			"product_id": 41058,
			"product_identity": "minimolefresnel",
			"external_asset": false,
			"holder_id": null,
			"depreciation_calculation_required": false,
			"location_rule_provisioned": false,
			"latest_contract_id": null,
			"manufacturer": null,
			"assigned_to_user_name": null,
			"asset_type": "FixedAsset",
			"sub_checked_out_to_full_name": null,
			"active_sub_checkout": null,
			"location_number": 1,
			"group": {
				"depreciation_rates": [
					{
						"id": 69696,
						"group_id": 102133,
						"depreciation_method_id": 149,
						"rate": "20.0",
						"created_at": "2022-03-05 22:11:22",
						"updated_at": "2022-03-05 22:11:22",
						"useful_life": 12,
						"depreciation_method_name": "Straight Line"
					}
				]
			},
			"primary_user": null,
			"assigned_to_user_email": null,
			"display_image": "/images/no-image.jpg",
			"location_name": "DFW",
			"depreciated_value": {
				"straight_line": "$31.95"
			},
			"action": "create",
			"rental_prices": {
				"per_minute": "0.0",
				"hourly": "0.0",
				"daily": "0.0",
				"weekly": "15.0",
				"monthly": "0.0"
			}
		},
		{
			"name": "Mini Mole Fresnel",
			"description": null,
			"price": "31.95",
			"identifier": "MMF010",
			"vendor_id": null,
			"group_id": 102133,
			"created_at": "2023-07-18 15:32:30",
			"updated_at": "2023-07-25 12:03:16",
			"checkin_due_on": null,
			"audit_pending": false,
			"sequence_num": 735,
			"product_model_number": null,
			"documents_count": 0,
			"services_count": 0,
			"comments_count": 1,
			"state": "available",
			"purchased_on": null,
			"retired_on": null,
			"location_id": 12371,
			"net_quantity": 1,
			"pending_verification": false,
			"salvage_value": "0.0",
			"package_id": null,
			"checkout_on": null,
			"inventory_threshold": 0,
			"retire_reason": null,
			"retire_comments": null,
			"sub_group_id": null,
			"location_based_threshold": 0,
			"arbitration": 2,
			"rent_collected": "0.0",
			"tax_free": false,
			"sale_price": "0.0",
			"retired_by_id": null,
			"featured_item": false,
			"visible_on_web_store": false,
			"is_processed": false,
			"rental_meter": 0,
			"rental_meter_threshold": 0,
			"initial_stock_quantity": 0,
			"quickbooks_item_id": null,
			"sub_checked_out_to_id": null,
			"advanced_pricing": false,
			"bulk_import_id": null,
			"purchase_order_id": null,
			"available_for_sale": false,
			"checkout_via_bundle": false,
			"clone_from_asset_id": 2898417,
			"itam_hardware_id": null,
			"created_by_itam": false,
			"hidden_on_web_store": false,
			"last_checked_out_at": null,
			"last_checked_in_at": null,
			"last_assigned_to_id": null,
			"synced_with_jira_at": null,
			"sunshine_id": null,
			"retire_reason_id": null,
			"it_asset_source": null,
			"current_meter_reading": "0.0",
			"custom_substate_id": null,
			"merge_date": null,
			"candidate_email": null,
			"default_excess_location_threshold": 0,
			"average_cost_per_unit": "0.0",
			"usage_meter_threshold": null,
			"send_usage_meter_threshold_recurring_alert": false,
			"update_counter": 0,
			"network_asset": false,
			"group_rule_provisioned": false,
			"last_history_id": null,
			"qbd_item_name": null,
			"item_audit_id": null,
			"product_id": 41058,
			"product_identity": "minimolefresnel",
			"external_asset": false,
			"holder_id": null,
			"depreciation_calculation_required": false,
			"location_rule_provisioned": false,
			"latest_contract_id": null,
			"manufacturer": null,
			"assigned_to_user_name": null,
			"asset_type": "FixedAsset",
			"sub_checked_out_to_full_name": null,
			"active_sub_checkout": null,
			"location_number": 1,
			"group": {
				"depreciation_rates": [
					{
						"id": 69696,
						"group_id": 102133,
						"depreciation_method_id": 149,
						"rate": "20.0",
						"created_at": "2022-03-05 22:11:22",
						"updated_at": "2022-03-05 22:11:22",
						"useful_life": 12,
						"depreciation_method_name": "Straight Line"
					}
				]
			},
			"primary_user": null,
			"assigned_to_user_email": null,
			"display_image": "/images/no-image.jpg",
			"location_name": "DFW",
			"depreciated_value": {
				"straight_line": "$31.95"
			},
			"action": "create",
			"rental_prices": {
				"per_minute": "0.0",
				"hourly": "0.0",
				"daily": "0.0",
				"weekly": "15.0",
				"monthly": "0.0"
			}
		},
		{
			"name": "Mini Mole Fresnel",
			"description": null,
			"price": "31.95",
			"identifier": "MMF011",
			"vendor_id": null,
			"group_id": 102133,
			"created_at": "2023-07-18 15:32:30",
			"updated_at": "2023-07-25 12:03:16",
			"checkin_due_on": null,
			"audit_pending": false,
			"sequence_num": 736,
			"product_model_number": null,
			"documents_count": 0,
			"services_count": 0,
			"comments_count": 1,
			"state": "available",
			"purchased_on": null,
			"retired_on": null,
			"location_id": 12371,
			"net_quantity": 1,
			"pending_verification": false,
			"salvage_value": "0.0",
			"package_id": null,
			"checkout_on": null,
			"inventory_threshold": 0,
			"retire_reason": null,
			"retire_comments": null,
			"sub_group_id": null,
			"location_based_threshold": 0,
			"arbitration": 2,
			"rent_collected": "0.0",
			"tax_free": false,
			"sale_price": "0.0",
			"retired_by_id": null,
			"featured_item": false,
			"visible_on_web_store": false,
			"is_processed": false,
			"rental_meter": 0,
			"rental_meter_threshold": 0,
			"initial_stock_quantity": 0,
			"quickbooks_item_id": null,
			"sub_checked_out_to_id": null,
			"advanced_pricing": false,
			"bulk_import_id": null,
			"purchase_order_id": null,
			"available_for_sale": false,
			"checkout_via_bundle": false,
			"clone_from_asset_id": 2898417,
			"itam_hardware_id": null,
			"created_by_itam": false,
			"hidden_on_web_store": false,
			"last_checked_out_at": null,
			"last_checked_in_at": null,
			"last_assigned_to_id": null,
			"synced_with_jira_at": null,
			"sunshine_id": null,
			"retire_reason_id": null,
			"it_asset_source": null,
			"current_meter_reading": "0.0",
			"custom_substate_id": null,
			"merge_date": null,
			"candidate_email": null,
			"default_excess_location_threshold": 0,
			"average_cost_per_unit": "0.0",
			"usage_meter_threshold": null,
			"send_usage_meter_threshold_recurring_alert": false,
			"update_counter": 0,
			"network_asset": false,
			"group_rule_provisioned": false,
			"last_history_id": null,
			"qbd_item_name": null,
			"item_audit_id": null,
			"product_id": 41058,
			"product_identity": "minimolefresnel",
			"external_asset": false,
			"holder_id": null,
			"depreciation_calculation_required": false,
			"location_rule_provisioned": false,
			"latest_contract_id": null,
			"manufacturer": null,
			"assigned_to_user_name": null,
			"asset_type": "FixedAsset",
			"sub_checked_out_to_full_name": null,
			"active_sub_checkout": null,
			"location_number": 1,
			"group": {
				"depreciation_rates": [
					{
						"id": 69696,
						"group_id": 102133,
						"depreciation_method_id": 149,
						"rate": "20.0",
						"created_at": "2022-03-05 22:11:22",
						"updated_at": "2022-03-05 22:11:22",
						"useful_life": 12,
						"depreciation_method_name": "Straight Line"
					}
				]
			},
			"primary_user": null,
			"assigned_to_user_email": null,
			"display_image": "/images/no-image.jpg",
			"location_name": "DFW",
			"depreciated_value": {
				"straight_line": "$31.95"
			},
			"action": "create",
			"rental_prices": {
				"per_minute": "0.0",
				"hourly": "0.0",
				"daily": "0.0",
				"weekly": "15.0",
				"monthly": "0.0"
			}
		},
		{
			"name": "Poseidon Aqua 2 Ultrasonic Ground Fog Generator",
			"description": "Froggy's Fog - Poseidon Aqua 2 is an event-ready, low-lying fog machine that creates thick clouds that hug the floor without the need for dry ice.  \r\n\r\n-Advanced Auto Water Refill System\r\n-Multi-Stage Humidity Control\r\n-Complete Fog and Fan Volume Control\r\n-Optimized Heater Core for Continuous Operation\r\n-Touch Screen LCD & DMX Control",
			"price": "0.0",
			"identifier": "PF001",
			"vendor_id": 65391,
			"group_id": 23000,
			"created_at": "2023-03-13 12:03:01",
			"updated_at": "2024-12-23 16:26:26",
			"checkin_due_on": null,
			"audit_pending": false,
			"sequence_num": 620,
			"product_model_number": null,
			"documents_count": 1,
			"services_count": 0,
			"comments_count": 0,
			"state": "available",
			"purchased_on": "2023-03-13",
			"retired_on": null,
			"location_id": 12371,
			"net_quantity": 1,
			"pending_verification": false,
			"salvage_value": "0.0",
			"package_id": null,
			"checkout_on": null,
			"inventory_threshold": 0,
			"retire_reason": null,
			"retire_comments": null,
			"sub_group_id": null,
			"location_based_threshold": 0,
			"arbitration": 2,
			"rent_collected": "4355.1",
			"tax_free": false,
			"sale_price": "0.0",
			"retired_by_id": null,
			"featured_item": false,
			"visible_on_web_store": false,
			"is_processed": false,
			"rental_meter": 0,
			"rental_meter_threshold": 0,
			"initial_stock_quantity": 0,
			"quickbooks_item_id": null,
			"sub_checked_out_to_id": null,
			"advanced_pricing": false,
			"bulk_import_id": null,
			"purchase_order_id": null,
			"available_for_sale": false,
			"checkout_via_bundle": false,
			"clone_from_asset_id": null,
			"itam_hardware_id": null,
			"created_by_itam": false,
			"hidden_on_web_store": false,
			"last_checked_out_at": "2024-10-22 12:35:21",
			"last_checked_in_at": "2024-06-24 11:29:36",
			"last_assigned_to_id": 21746,
			"synced_with_jira_at": null,
			"sunshine_id": null,
			"retire_reason_id": null,
			"it_asset_source": null,
			"current_meter_reading": "0.0",
			"custom_substate_id": null,
			"merge_date": null,
			"candidate_email": null,
			"default_excess_location_threshold": 0,
			"average_cost_per_unit": "0.0",
			"usage_meter_threshold": null,
			"send_usage_meter_threshold_recurring_alert": false,
			"update_counter": 0,
			"network_asset": false,
			"group_rule_provisioned": false,
			"last_history_id": 10699982,
			"qbd_item_name": null,
			"item_audit_id": null,
			"product_id": 41057,
			"product_identity": "poseidonaqua2ultrasonicgroundfoggenerator",
			"external_asset": false,
			"holder_id": null,
			"depreciation_calculation_required": false,
			"location_rule_provisioned": false,
			"latest_contract_id": null,
			"manufacturer": null,
			"assigned_to_user_name": null,
			"asset_type": "FixedAsset",
			"sub_checked_out_to_full_name": null,
			"active_sub_checkout": null,
			"location_number": 1,
			"group": {
				"depreciation_rates": [
					{
						"id": 2777,
						"group_id": 23000,
						"depreciation_method_id": 149,
						"rate": "20.0",
						"created_at": "2020-08-09 04:52:55",
						"updated_at": "2020-08-09 04:52:55",
						"useful_life": 12,
						"depreciation_method_name": "Straight Line"
					}
				]
			},
			"primary_user": null,
			"assigned_to_user_email": null,
			"display_image": "https://s3.amazonaws.com/docs.ezrentout.com/attachments/documents/1851318/original/FF.PoseidonAqua2.jpg?X-Amz-Algorithm=AWS4-HMAC-SHA256&X-Amz-Credential=AKIAVKFZ2DWIL7B6J3WK%2F20250717%2Fus-east-1%2Fs3%2Faws4_request&X-Amz-Date=20250717T205252Z&X-Amz-Expires=43200&X-Amz-SignedHeaders=host&X-Amz-Signature=55b5d0e067d2fadd377b21e926f96e96c5d063d0c87ea7bf3d7ecee1da000aaf",
			"location_name": "DFW",
			"depreciated_value": {
				"straight_line": "$0.00"
			},
			"action": "create",
			"rental_prices": {
				"per_minute": "0.0",
				"hourly": "0.0",
				"daily": "0.0",
				"weekly": "241.95",
				"monthly": "0.0"
			}
		},
		{
			"name": "Poseidon Aqua 2 Ultrasonic Ground Fog Generator",
			"description": "Froggy's Fog - Poseidon Aqua 2 is an event-ready, low-lying fog machine that creates thick clouds that hug the floor without the need for dry ice.  \r\n\r\n-Advanced Auto Water Refill System\r\n-Multi-Stage Humidity Control\r\n-Complete Fog and Fan Volume Control\r\n-Optimized Heater Core for Continuous Operation\r\n-Touch Screen LCD & DMX Control",
			"price": "0.0",
			"identifier": "PF002",
			"vendor_id": 65391,
			"group_id": 23000,
			"created_at": "2023-03-13 12:11:37",
			"updated_at": "2024-12-23 16:26:26",
			"checkin_due_on": null,
			"audit_pending": false,
			"sequence_num": 621,
			"product_model_number": null,
			"documents_count": 1,
			"services_count": 0,
			"comments_count": 0,
			"state": "available",
			"purchased_on": "2023-03-13",
			"retired_on": null,
			"location_id": 12371,
			"net_quantity": 1,
			"pending_verification": false,
			"salvage_value": "0.0",
			"package_id": null,
			"checkout_on": null,
			"inventory_threshold": 0,
			"retire_reason": null,
			"retire_comments": null,
			"sub_group_id": null,
			"location_based_threshold": 0,
			"arbitration": 2,
			"rent_collected": "3871.2",
			"tax_free": false,
			"sale_price": "0.0",
			"retired_by_id": null,
			"featured_item": false,
			"visible_on_web_store": false,
			"is_processed": false,
			"rental_meter": 0,
			"rental_meter_threshold": 0,
			"initial_stock_quantity": 0,
			"quickbooks_item_id": null,
			"sub_checked_out_to_id": null,
			"advanced_pricing": false,
			"bulk_import_id": null,
			"purchase_order_id": null,
			"available_for_sale": false,
			"checkout_via_bundle": false,
			"clone_from_asset_id": 2831411,
			"itam_hardware_id": null,
			"created_by_itam": false,
			"hidden_on_web_store": false,
			"last_checked_out_at": "2024-11-05 15:10:09",
			"last_checked_in_at": "2023-07-11 10:49:51",
			"last_assigned_to_id": 21833,
			"synced_with_jira_at": null,
			"sunshine_id": null,
			"retire_reason_id": null,
			"it_asset_source": null,
			"current_meter_reading": "0.0",
			"custom_substate_id": null,
			"merge_date": null,
			"candidate_email": null,
			"default_excess_location_threshold": 0,
			"average_cost_per_unit": "0.0",
			"usage_meter_threshold": null,
			"send_usage_meter_threshold_recurring_alert": false,
			"update_counter": 0,
			"network_asset": false,
			"group_rule_provisioned": false,
			"last_history_id": 10734177,
			"qbd_item_name": null,
			"item_audit_id": null,
			"product_id": 41057,
			"product_identity": "poseidonaqua2ultrasonicgroundfoggenerator",
			"external_asset": false,
			"holder_id": null,
			"depreciation_calculation_required": false,
			"location_rule_provisioned": false,
			"latest_contract_id": null,
			"manufacturer": null,
			"assigned_to_user_name": null,
			"asset_type": "FixedAsset",
			"sub_checked_out_to_full_name": null,
			"active_sub_checkout": null,
			"location_number": 1,
			"group": {
				"depreciation_rates": [
					{
						"id": 2777,
						"group_id": 23000,
						"depreciation_method_id": 149,
						"rate": "20.0",
						"created_at": "2020-08-09 04:52:55",
						"updated_at": "2020-08-09 04:52:55",
						"useful_life": 12,
						"depreciation_method_name": "Straight Line"
					}
				]
			},
			"primary_user": null,
			"assigned_to_user_email": null,
			"display_image": "https://s3.amazonaws.com/docs.ezrentout.com/attachments/documents/1851318/original/FF.PoseidonAqua2.jpg?X-Amz-Algorithm=AWS4-HMAC-SHA256&X-Amz-Credential=AKIAVKFZ2DWIL7B6J3WK%2F20250717%2Fus-east-1%2Fs3%2Faws4_request&X-Amz-Date=20250717T205252Z&X-Amz-Expires=43200&X-Amz-SignedHeaders=host&X-Amz-Signature=55b5d0e067d2fadd377b21e926f96e96c5d063d0c87ea7bf3d7ecee1da000aaf",
			"location_name": "DFW",
			"depreciated_value": {
				"straight_line": "$0.00"
			},
			"action": "create",
			"rental_prices": {
				"per_minute": "0.0",
				"hourly": "0.0",
				"daily": "0.0",
				"weekly": "241.95",
				"monthly": "0.0"
			}
		},
		{
			"name": "Poseidon Aqua 2 Ultrasonic Ground Fog Generator",
			"description": "Froggy's Fog - Poseidon Aqua 2 is an event-ready, low-lying fog machine that creates thick clouds that hug the floor without the need for dry ice.  \r\n\r\n-Advanced Auto Water Refill System\r\n-Multi-Stage Humidity Control\r\n-Complete Fog and Fan Volume Control\r\n-Optimized Heater Core for Continuous Operation\r\n-Touch Screen LCD & DMX Control",
			"price": "0.0",
			"identifier": "PF-003",
			"vendor_id": 65391,
			"group_id": 23000,
			"created_at": "2024-01-29 16:54:58",
			"updated_at": "2024-11-13 17:37:27",
			"checkin_due_on": null,
			"audit_pending": false,
			"sequence_num": 753,
			"product_model_number": null,
			"documents_count": 1,
			"services_count": 0,
			"comments_count": 0,
			"state": "available",
			"purchased_on": "2023-03-13",
			"retired_on": null,
			"location_id": 12371,
			"net_quantity": 1,
			"pending_verification": false,
			"salvage_value": "0.0",
			"package_id": null,
			"checkout_on": null,
			"inventory_threshold": 0,
			"retire_reason": null,
			"retire_comments": null,
			"sub_group_id": null,
			"location_based_threshold": 0,
			"arbitration": 2,
			"rent_collected": "967.8",
			"tax_free": false,
			"sale_price": "0.0",
			"retired_by_id": null,
			"featured_item": false,
			"visible_on_web_store": false,
			"is_processed": false,
			"rental_meter": 0,
			"rental_meter_threshold": 0,
			"initial_stock_quantity": 0,
			"quickbooks_item_id": null,
			"sub_checked_out_to_id": null,
			"advanced_pricing": false,
			"bulk_import_id": null,
			"purchase_order_id": null,
			"available_for_sale": false,
			"checkout_via_bundle": false,
			"clone_from_asset_id": 2831412,
			"itam_hardware_id": null,
			"created_by_itam": false,
			"hidden_on_web_store": false,
			"last_checked_out_at": "2024-11-05 15:10:09",
			"last_checked_in_at": "2024-06-24 11:29:36",
			"last_assigned_to_id": 21833,
			"synced_with_jira_at": null,
			"sunshine_id": null,
			"retire_reason_id": null,
			"it_asset_source": null,
			"current_meter_reading": "0.0",
			"custom_substate_id": null,
			"merge_date": null,
			"candidate_email": null,
			"default_excess_location_threshold": 0,
			"average_cost_per_unit": "0.0",
			"usage_meter_threshold": null,
			"send_usage_meter_threshold_recurring_alert": false,
			"update_counter": 0,
			"network_asset": false,
			"group_rule_provisioned": false,
			"last_history_id": 10734178,
			"qbd_item_name": null,
			"item_audit_id": null,
			"product_id": 41057,
			"product_identity": "poseidonaqua2ultrasonicgroundfoggenerator",
			"external_asset": false,
			"holder_id": null,
			"depreciation_calculation_required": false,
			"location_rule_provisioned": false,
			"latest_contract_id": null,
			"manufacturer": null,
			"assigned_to_user_name": null,
			"asset_type": "FixedAsset",
			"sub_checked_out_to_full_name": null,
			"active_sub_checkout": null,
			"location_number": 1,
			"group": {
				"depreciation_rates": [
					{
						"id": 2777,
						"group_id": 23000,
						"depreciation_method_id": 149,
						"rate": "20.0",
						"created_at": "2020-08-09 04:52:55",
						"updated_at": "2020-08-09 04:52:55",
						"useful_life": 12,
						"depreciation_method_name": "Straight Line"
					}
				]
			},
			"primary_user": null,
			"assigned_to_user_email": null,
			"display_image": "https://s3.amazonaws.com/docs.ezrentout.com/attachments/documents/1851318/original/FF.PoseidonAqua2.jpg?X-Amz-Algorithm=AWS4-HMAC-SHA256&X-Amz-Credential=AKIAVKFZ2DWIL7B6J3WK%2F20250717%2Fus-east-1%2Fs3%2Faws4_request&X-Amz-Date=20250717T205252Z&X-Amz-Expires=43200&X-Amz-SignedHeaders=host&X-Amz-Signature=55b5d0e067d2fadd377b21e926f96e96c5d063d0c87ea7bf3d7ecee1da000aaf",
			"location_name": "DFW",
			"depreciated_value": {
				"straight_line": "$0.00"
			},
			"action": "create",
			"rental_prices": {
				"per_minute": "0.0",
				"hourly": "0.0",
				"daily": "0.0",
				"weekly": "241.95",
				"monthly": "0.0"
			}
		},
		{
			"name": "Remedy RGBW",
			"description": "RGBW LED battery, wireless DMX ",
			"price": "0.0",
			"identifier": "LED-R001",
			"vendor_id": null,
			"group_id": 22999,
			"created_at": "2023-06-12 14:04:20",
			"updated_at": "2024-02-12 14:53:23",
			"checkin_due_on": null,
			"audit_pending": false,
			"sequence_num": 632,
			"product_model_number": null,
			"documents_count": 1,
			"services_count": 0,
			"comments_count": 0,
			"state": "available",
			"purchased_on": "2017-12-02",
			"retired_on": null,
			"location_id": 12371,
			"net_quantity": 1,
			"pending_verification": false,
			"salvage_value": "0.0",
			"package_id": null,
			"checkout_on": null,
			"inventory_threshold": 0,
			"retire_reason": null,
			"retire_comments": null,
			"sub_group_id": null,
			"location_based_threshold": 0,
			"arbitration": 2,
			"rent_collected": "223.6",
			"tax_free": false,
			"sale_price": "0.0",
			"retired_by_id": null,
			"featured_item": false,
			"visible_on_web_store": false,
			"is_processed": false,
			"rental_meter": 0,
			"rental_meter_threshold": 0,
			"initial_stock_quantity": 0,
			"quickbooks_item_id": null,
			"sub_checked_out_to_id": null,
			"advanced_pricing": false,
			"bulk_import_id": null,
			"purchase_order_id": null,
			"available_for_sale": false,
			"checkout_via_bundle": false,
			"clone_from_asset_id": null,
			"itam_hardware_id": null,
			"created_by_itam": false,
			"hidden_on_web_store": false,
			"last_checked_out_at": "2024-02-09 13:51:00",
			"last_checked_in_at": "2023-07-11 10:49:54",
			"last_assigned_to_id": 21718,
			"synced_with_jira_at": null,
			"sunshine_id": null,
			"retire_reason_id": null,
			"it_asset_source": null,
			"current_meter_reading": "0.0",
			"custom_substate_id": null,
			"merge_date": null,
			"candidate_email": null,
			"default_excess_location_threshold": 0,
			"average_cost_per_unit": "0.0",
			"usage_meter_threshold": null,
			"send_usage_meter_threshold_recurring_alert": false,
			"update_counter": 0,
			"network_asset": false,
			"group_rule_provisioned": false,
			"last_history_id": 9476034,
			"qbd_item_name": null,
			"item_audit_id": null,
			"product_id": 41060,
			"product_identity": "remedyrgbw",
			"external_asset": false,
			"holder_id": null,
			"depreciation_calculation_required": false,
			"location_rule_provisioned": false,
			"latest_contract_id": null,
			"manufacturer": null,
			"assigned_to_user_name": null,
			"asset_type": "FixedAsset",
			"sub_checked_out_to_full_name": null,
			"active_sub_checkout": null,
			"location_number": 1,
			"group": {
				"depreciation_rates": [
					{
						"id": 2776,
						"group_id": 22999,
						"depreciation_method_id": 149,
						"rate": "20.0",
						"created_at": "2020-08-09 04:52:55",
						"updated_at": "2020-08-09 04:52:55",
						"useful_life": 12,
						"depreciation_method_name": "Straight Line"
					}
				]
			},
			"primary_user": null,
			"assigned_to_user_email": null,
			"display_image": "https://s3.amazonaws.com/docs.ezrentout.com/attachments/documents/1992990/original/Logo%28whiteexpanded%29blk.jpg?X-Amz-Algorithm=AWS4-HMAC-SHA256&X-Amz-Credential=AKIAVKFZ2DWIL7B6J3WK%2F20250717%2Fus-east-1%2Fs3%2Faws4_request&X-Amz-Date=20250717T205252Z&X-Amz-Expires=43200&X-Amz-SignedHeaders=host&X-Amz-Signature=6ce737a818b01acba16e861a19de6f3d7f0579f5ec0aed965e3c9053b078380c",
			"location_name": "DFW",
			"depreciated_value": {
				"straight_line": "$0.00"
			},
			"action": "create",
			"rental_prices": {
				"per_minute": "0.0",
				"hourly": "0.0",
				"daily": "0.0",
				"weekly": "55.9",
				"monthly": "0.0"
			}
		},
		{
			"name": "Remedy RGBW",
			"description": "RGBW LED battery, wireless DMX ",
			"price": "0.0",
			"identifier": "LED-R002",
			"vendor_id": null,
			"group_id": 22999,
			"created_at": "2023-06-12 14:06:14",
			"updated_at": "2024-02-12 14:53:23",
			"checkin_due_on": null,
			"audit_pending": false,
			"sequence_num": 633,
			"product_model_number": null,
			"documents_count": 1,
			"services_count": 0,
			"comments_count": 0,
			"state": "available",
			"purchased_on": "2017-12-02",
			"retired_on": null,
			"location_id": 12371,
			"net_quantity": 1,
			"pending_verification": false,
			"salvage_value": "0.0",
			"package_id": null,
			"checkout_on": null,
			"inventory_threshold": 0,
			"retire_reason": null,
			"retire_comments": null,
			"sub_group_id": null,
			"location_based_threshold": 0,
			"arbitration": 2,
			"rent_collected": "223.6",
			"tax_free": false,
			"sale_price": "0.0",
			"retired_by_id": null,
			"featured_item": false,
			"visible_on_web_store": false,
			"is_processed": false,
			"rental_meter": 0,
			"rental_meter_threshold": 0,
			"initial_stock_quantity": 0,
			"quickbooks_item_id": null,
			"sub_checked_out_to_id": null,
			"advanced_pricing": false,
			"bulk_import_id": null,
			"purchase_order_id": null,
			"available_for_sale": false,
			"checkout_via_bundle": false,
			"clone_from_asset_id": 2918095,
			"itam_hardware_id": null,
			"created_by_itam": false,
			"hidden_on_web_store": false,
			"last_checked_out_at": "2024-02-09 13:51:00",
			"last_checked_in_at": "2023-07-11 10:49:54",
			"last_assigned_to_id": 21718,
			"synced_with_jira_at": null,
			"sunshine_id": null,
			"retire_reason_id": null,
			"it_asset_source": null,
			"current_meter_reading": "0.0",
			"custom_substate_id": null,
			"merge_date": null,
			"candidate_email": null,
			"default_excess_location_threshold": 0,
			"average_cost_per_unit": "0.0",
			"usage_meter_threshold": null,
			"send_usage_meter_threshold_recurring_alert": false,
			"update_counter": 0,
			"network_asset": false,
			"group_rule_provisioned": false,
			"last_history_id": 9476035,
			"qbd_item_name": null,
			"item_audit_id": null,
			"product_id": 41060,
			"product_identity": "remedyrgbw",
			"external_asset": false,
			"holder_id": null,
			"depreciation_calculation_required": false,
			"location_rule_provisioned": false,
			"latest_contract_id": null,
			"manufacturer": null,
			"assigned_to_user_name": null,
			"asset_type": "FixedAsset",
			"sub_checked_out_to_full_name": null,
			"active_sub_checkout": null,
			"location_number": 1,
			"group": {
				"depreciation_rates": [
					{
						"id": 2776,
						"group_id": 22999,
						"depreciation_method_id": 149,
						"rate": "20.0",
						"created_at": "2020-08-09 04:52:55",
						"updated_at": "2020-08-09 04:52:55",
						"useful_life": 12,
						"depreciation_method_name": "Straight Line"
					}
				]
			},
			"primary_user": null,
			"assigned_to_user_email": null,
			"display_image": "https://s3.amazonaws.com/docs.ezrentout.com/attachments/documents/1992990/original/Logo%28whiteexpanded%29blk.jpg?X-Amz-Algorithm=AWS4-HMAC-SHA256&X-Amz-Credential=AKIAVKFZ2DWIL7B6J3WK%2F20250717%2Fus-east-1%2Fs3%2Faws4_request&X-Amz-Date=20250717T205252Z&X-Amz-Expires=43200&X-Amz-SignedHeaders=host&X-Amz-Signature=6ce737a818b01acba16e861a19de6f3d7f0579f5ec0aed965e3c9053b078380c",
			"location_name": "DFW",
			"depreciated_value": {
				"straight_line": "$0.00"
			},
			"action": "create",
			"rental_prices": {
				"per_minute": "0.0",
				"hourly": "0.0",
				"daily": "0.0",
				"weekly": "55.9",
				"monthly": "0.0"
			}
		},
		{
			"name": "Remedy RGBW",
			"description": "RGBW LED battery, wireless DMX ",
			"price": "0.0",
			"identifier": "LED-R003",
			"vendor_id": null,
			"group_id": 22999,
			"created_at": "2023-06-12 14:06:14",
			"updated_at": "2024-02-12 14:53:23",
			"checkin_due_on": null,
			"audit_pending": false,
			"sequence_num": 634,
			"product_model_number": null,
			"documents_count": 1,
			"services_count": 0,
			"comments_count": 0,
			"state": "available",
			"purchased_on": "2017-12-02",
			"retired_on": null,
			"location_id": 12371,
			"net_quantity": 1,
			"pending_verification": false,
			"salvage_value": "0.0",
			"package_id": null,
			"checkout_on": null,
			"inventory_threshold": 0,
			"retire_reason": null,
			"retire_comments": null,
			"sub_group_id": null,
			"location_based_threshold": 0,
			"arbitration": 2,
			"rent_collected": "223.6",
			"tax_free": false,
			"sale_price": "0.0",
			"retired_by_id": null,
			"featured_item": false,
			"visible_on_web_store": false,
			"is_processed": false,
			"rental_meter": 0,
			"rental_meter_threshold": 0,
			"initial_stock_quantity": 0,
			"quickbooks_item_id": null,
			"sub_checked_out_to_id": null,
			"advanced_pricing": false,
			"bulk_import_id": null,
			"purchase_order_id": null,
			"available_for_sale": false,
			"checkout_via_bundle": false,
			"clone_from_asset_id": 2918095,
			"itam_hardware_id": null,
			"created_by_itam": false,
			"hidden_on_web_store": false,
			"last_checked_out_at": "2024-02-09 13:51:00",
			"last_checked_in_at": "2023-07-11 10:49:54",
			"last_assigned_to_id": 21718,
			"synced_with_jira_at": null,
			"sunshine_id": null,
			"retire_reason_id": null,
			"it_asset_source": null,
			"current_meter_reading": "0.0",
			"custom_substate_id": null,
			"merge_date": null,
			"candidate_email": null,
			"default_excess_location_threshold": 0,
			"average_cost_per_unit": "0.0",
			"usage_meter_threshold": null,
			"send_usage_meter_threshold_recurring_alert": false,
			"update_counter": 0,
			"network_asset": false,
			"group_rule_provisioned": false,
			"last_history_id": 9476036,
			"qbd_item_name": null,
			"item_audit_id": null,
			"product_id": 41060,
			"product_identity": "remedyrgbw",
			"external_asset": false,
			"holder_id": null,
			"depreciation_calculation_required": false,
			"location_rule_provisioned": false,
			"latest_contract_id": null,
			"manufacturer": null,
			"assigned_to_user_name": null,
			"asset_type": "FixedAsset",
			"sub_checked_out_to_full_name": null,
			"active_sub_checkout": null,
			"location_number": 1,
			"group": {
				"depreciation_rates": [
					{
						"id": 2776,
						"group_id": 22999,
						"depreciation_method_id": 149,
						"rate": "20.0",
						"created_at": "2020-08-09 04:52:55",
						"updated_at": "2020-08-09 04:52:55",
						"useful_life": 12,
						"depreciation_method_name": "Straight Line"
					}
				]
			},
			"primary_user": null,
			"assigned_to_user_email": null,
			"display_image": "https://s3.amazonaws.com/docs.ezrentout.com/attachments/documents/1992990/original/Logo%28whiteexpanded%29blk.jpg?X-Amz-Algorithm=AWS4-HMAC-SHA256&X-Amz-Credential=AKIAVKFZ2DWIL7B6J3WK%2F20250717%2Fus-east-1%2Fs3%2Faws4_request&X-Amz-Date=20250717T205252Z&X-Amz-Expires=43200&X-Amz-SignedHeaders=host&X-Amz-Signature=6ce737a818b01acba16e861a19de6f3d7f0579f5ec0aed965e3c9053b078380c",
			"location_name": "DFW",
			"depreciated_value": {
				"straight_line": "$0.00"
			},
			"action": "create",
			"rental_prices": {
				"per_minute": "0.0",
				"hourly": "0.0",
				"daily": "0.0",
				"weekly": "55.9",
				"monthly": "0.0"
			}
		},
		{
			"name": "Remedy RGBW",
			"description": "RGBW LED battery, wireless DMX ",
			"price": "0.0",
			"identifier": "LED-R004",
			"vendor_id": null,
			"group_id": 22999,
			"created_at": "2023-06-12 14:06:14",
			"updated_at": "2023-07-11 10:51:00",
			"checkin_due_on": null,
			"audit_pending": false,
			"sequence_num": 635,
			"product_model_number": null,
			"documents_count": 1,
			"services_count": 0,
			"comments_count": 0,
			"state": "available",
			"purchased_on": "2017-12-02",
			"retired_on": null,
			"location_id": 12371,
			"net_quantity": 1,
			"pending_verification": false,
			"salvage_value": "0.0",
			"package_id": null,
			"checkout_on": null,
			"inventory_threshold": 0,
			"retire_reason": null,
			"retire_comments": null,
			"sub_group_id": null,
			"location_based_threshold": 0,
			"arbitration": 2,
			"rent_collected": "167.7",
			"tax_free": false,
			"sale_price": "0.0",
			"retired_by_id": null,
			"featured_item": false,
			"visible_on_web_store": false,
			"is_processed": false,
			"rental_meter": 0,
			"rental_meter_threshold": 0,
			"initial_stock_quantity": 0,
			"quickbooks_item_id": null,
			"sub_checked_out_to_id": null,
			"advanced_pricing": false,
			"bulk_import_id": null,
			"purchase_order_id": null,
			"available_for_sale": false,
			"checkout_via_bundle": false,
			"clone_from_asset_id": 2918095,
			"itam_hardware_id": null,
			"created_by_itam": false,
			"hidden_on_web_store": false,
			"last_checked_out_at": "2023-06-26 12:09:48",
			"last_checked_in_at": null,
			"last_assigned_to_id": 21937,
			"synced_with_jira_at": null,
			"sunshine_id": null,
			"retire_reason_id": null,
			"it_asset_source": null,
			"current_meter_reading": "0.0",
			"custom_substate_id": null,
			"merge_date": null,
			"candidate_email": null,
			"default_excess_location_threshold": 0,
			"average_cost_per_unit": "0.0",
			"usage_meter_threshold": null,
			"send_usage_meter_threshold_recurring_alert": false,
			"update_counter": 0,
			"network_asset": false,
			"group_rule_provisioned": false,
			"last_history_id": 8341675,
			"qbd_item_name": null,
			"item_audit_id": null,
			"product_id": 41060,
			"product_identity": "remedyrgbw",
			"external_asset": false,
			"holder_id": null,
			"depreciation_calculation_required": false,
			"location_rule_provisioned": false,
			"latest_contract_id": null,
			"manufacturer": null,
			"assigned_to_user_name": null,
			"asset_type": "FixedAsset",
			"sub_checked_out_to_full_name": null,
			"active_sub_checkout": null,
			"location_number": 1,
			"group": {
				"depreciation_rates": [
					{
						"id": 2776,
						"group_id": 22999,
						"depreciation_method_id": 149,
						"rate": "20.0",
						"created_at": "2020-08-09 04:52:55",
						"updated_at": "2020-08-09 04:52:55",
						"useful_life": 12,
						"depreciation_method_name": "Straight Line"
					}
				]
			},
			"primary_user": null,
			"assigned_to_user_email": null,
			"display_image": "https://s3.amazonaws.com/docs.ezrentout.com/attachments/documents/1992990/original/Logo%28whiteexpanded%29blk.jpg?X-Amz-Algorithm=AWS4-HMAC-SHA256&X-Amz-Credential=AKIAVKFZ2DWIL7B6J3WK%2F20250717%2Fus-east-1%2Fs3%2Faws4_request&X-Amz-Date=20250717T205252Z&X-Amz-Expires=43200&X-Amz-SignedHeaders=host&X-Amz-Signature=6ce737a818b01acba16e861a19de6f3d7f0579f5ec0aed965e3c9053b078380c",
			"location_name": "DFW",
			"depreciated_value": {
				"straight_line": "$0.00"
			},
			"action": "create",
			"rental_prices": {
				"per_minute": "0.0",
				"hourly": "0.0",
				"daily": "0.0",
				"weekly": "55.9",
				"monthly": "0.0"
			}
		},
		{
			"name": "Remedy RGBW",
			"description": "RGBW LED battery, wireless DMX ",
			"price": "0.0",
			"identifier": "LED-R005",
			"vendor_id": null,
			"group_id": 22999,
			"created_at": "2023-06-12 14:06:14",
			"updated_at": "2023-07-11 10:51:00",
			"checkin_due_on": null,
			"audit_pending": false,
			"sequence_num": 636,
			"product_model_number": null,
			"documents_count": 1,
			"services_count": 0,
			"comments_count": 0,
			"state": "available",
			"purchased_on": "2017-12-02",
			"retired_on": null,
			"location_id": 12371,
			"net_quantity": 1,
			"pending_verification": false,
			"salvage_value": "0.0",
			"package_id": null,
			"checkout_on": null,
			"inventory_threshold": 0,
			"retire_reason": null,
			"retire_comments": null,
			"sub_group_id": null,
			"location_based_threshold": 0,
			"arbitration": 2,
			"rent_collected": "167.7",
			"tax_free": false,
			"sale_price": "0.0",
			"retired_by_id": null,
			"featured_item": false,
			"visible_on_web_store": false,
			"is_processed": false,
			"rental_meter": 0,
			"rental_meter_threshold": 0,
			"initial_stock_quantity": 0,
			"quickbooks_item_id": null,
			"sub_checked_out_to_id": null,
			"advanced_pricing": false,
			"bulk_import_id": null,
			"purchase_order_id": null,
			"available_for_sale": false,
			"checkout_via_bundle": false,
			"clone_from_asset_id": 2918095,
			"itam_hardware_id": null,
			"created_by_itam": false,
			"hidden_on_web_store": false,
			"last_checked_out_at": "2023-06-26 12:09:48",
			"last_checked_in_at": null,
			"last_assigned_to_id": 21937,
			"synced_with_jira_at": null,
			"sunshine_id": null,
			"retire_reason_id": null,
			"it_asset_source": null,
			"current_meter_reading": "0.0",
			"custom_substate_id": null,
			"merge_date": null,
			"candidate_email": null,
			"default_excess_location_threshold": 0,
			"average_cost_per_unit": "0.0",
			"usage_meter_threshold": null,
			"send_usage_meter_threshold_recurring_alert": false,
			"update_counter": 0,
			"network_asset": false,
			"group_rule_provisioned": false,
			"last_history_id": 8341676,
			"qbd_item_name": null,
			"item_audit_id": null,
			"product_id": 41060,
			"product_identity": "remedyrgbw",
			"external_asset": false,
			"holder_id": null,
			"depreciation_calculation_required": false,
			"location_rule_provisioned": false,
			"latest_contract_id": null,
			"manufacturer": null,
			"assigned_to_user_name": null,
			"asset_type": "FixedAsset",
			"sub_checked_out_to_full_name": null,
			"active_sub_checkout": null,
			"location_number": 1,
			"group": {
				"depreciation_rates": [
					{
						"id": 2776,
						"group_id": 22999,
						"depreciation_method_id": 149,
						"rate": "20.0",
						"created_at": "2020-08-09 04:52:55",
						"updated_at": "2020-08-09 04:52:55",
						"useful_life": 12,
						"depreciation_method_name": "Straight Line"
					}
				]
			},
			"primary_user": null,
			"assigned_to_user_email": null,
			"display_image": "https://s3.amazonaws.com/docs.ezrentout.com/attachments/documents/1992990/original/Logo%28whiteexpanded%29blk.jpg?X-Amz-Algorithm=AWS4-HMAC-SHA256&X-Amz-Credential=AKIAVKFZ2DWIL7B6J3WK%2F20250717%2Fus-east-1%2Fs3%2Faws4_request&X-Amz-Date=20250717T205252Z&X-Amz-Expires=43200&X-Amz-SignedHeaders=host&X-Amz-Signature=6ce737a818b01acba16e861a19de6f3d7f0579f5ec0aed965e3c9053b078380c",
			"location_name": "DFW",
			"depreciated_value": {
				"straight_line": "$0.00"
			},
			"action": "create",
			"rental_prices": {
				"per_minute": "0.0",
				"hourly": "0.0",
				"daily": "0.0",
				"weekly": "55.9",
				"monthly": "0.0"
			}
		},
		{
			"name": "Remedy RGBW",
			"description": "RGBW LED battery, wireless DMX ",
			"price": "0.0",
			"identifier": "LED-R006",
			"vendor_id": null,
			"group_id": 22999,
			"created_at": "2023-06-12 14:06:14",
			"updated_at": "2023-07-11 10:51:00",
			"checkin_due_on": null,
			"audit_pending": false,
			"sequence_num": 637,
			"product_model_number": null,
			"documents_count": 1,
			"services_count": 0,
			"comments_count": 0,
			"state": "available",
			"purchased_on": "2017-12-02",
			"retired_on": null,
			"location_id": 12371,
			"net_quantity": 1,
			"pending_verification": false,
			"salvage_value": "0.0",
			"package_id": null,
			"checkout_on": null,
			"inventory_threshold": 0,
			"retire_reason": null,
			"retire_comments": null,
			"sub_group_id": null,
			"location_based_threshold": 0,
			"arbitration": 2,
			"rent_collected": "167.7",
			"tax_free": false,
			"sale_price": "0.0",
			"retired_by_id": null,
			"featured_item": false,
			"visible_on_web_store": false,
			"is_processed": false,
			"rental_meter": 0,
			"rental_meter_threshold": 0,
			"initial_stock_quantity": 0,
			"quickbooks_item_id": null,
			"sub_checked_out_to_id": null,
			"advanced_pricing": false,
			"bulk_import_id": null,
			"purchase_order_id": null,
			"available_for_sale": false,
			"checkout_via_bundle": false,
			"clone_from_asset_id": 2918095,
			"itam_hardware_id": null,
			"created_by_itam": false,
			"hidden_on_web_store": false,
			"last_checked_out_at": "2023-06-26 12:09:48",
			"last_checked_in_at": null,
			"last_assigned_to_id": 21937,
			"synced_with_jira_at": null,
			"sunshine_id": null,
			"retire_reason_id": null,
			"it_asset_source": null,
			"current_meter_reading": "0.0",
			"custom_substate_id": null,
			"merge_date": null,
			"candidate_email": null,
			"default_excess_location_threshold": 0,
			"average_cost_per_unit": "0.0",
			"usage_meter_threshold": null,
			"send_usage_meter_threshold_recurring_alert": false,
			"update_counter": 0,
			"network_asset": false,
			"group_rule_provisioned": false,
			"last_history_id": 8341677,
			"qbd_item_name": null,
			"item_audit_id": null,
			"product_id": 41060,
			"product_identity": "remedyrgbw",
			"external_asset": false,
			"holder_id": null,
			"depreciation_calculation_required": false,
			"location_rule_provisioned": false,
			"latest_contract_id": null,
			"manufacturer": null,
			"assigned_to_user_name": null,
			"asset_type": "FixedAsset",
			"sub_checked_out_to_full_name": null,
			"active_sub_checkout": null,
			"location_number": 1,
			"group": {
				"depreciation_rates": [
					{
						"id": 2776,
						"group_id": 22999,
						"depreciation_method_id": 149,
						"rate": "20.0",
						"created_at": "2020-08-09 04:52:55",
						"updated_at": "2020-08-09 04:52:55",
						"useful_life": 12,
						"depreciation_method_name": "Straight Line"
					}
				]
			},
			"primary_user": null,
			"assigned_to_user_email": null,
			"display_image": "https://s3.amazonaws.com/docs.ezrentout.com/attachments/documents/1992990/original/Logo%28whiteexpanded%29blk.jpg?X-Amz-Algorithm=AWS4-HMAC-SHA256&X-Amz-Credential=AKIAVKFZ2DWIL7B6J3WK%2F20250717%2Fus-east-1%2Fs3%2Faws4_request&X-Amz-Date=20250717T205252Z&X-Amz-Expires=43200&X-Amz-SignedHeaders=host&X-Amz-Signature=6ce737a818b01acba16e861a19de6f3d7f0579f5ec0aed965e3c9053b078380c",
			"location_name": "DFW",
			"depreciated_value": {
				"straight_line": "$0.00"
			},
			"action": "create",
			"rental_prices": {
				"per_minute": "0.0",
				"hourly": "0.0",
				"daily": "0.0",
				"weekly": "55.9",
				"monthly": "0.0"
			}
		},
		{
			"name": "Remedy RGBW",
			"description": "RGBW LED battery, wireless DMX ",
			"price": "0.0",
			"identifier": "LED-R007",
			"vendor_id": null,
			"group_id": 22999,
			"created_at": "2023-06-12 14:06:14",
			"updated_at": "2023-06-21 11:06:57",
			"checkin_due_on": null,
			"audit_pending": false,
			"sequence_num": 638,
			"product_model_number": null,
			"documents_count": 1,
			"services_count": 0,
			"comments_count": 0,
			"state": "available",
			"purchased_on": "2017-12-02",
			"retired_on": null,
			"location_id": 12371,
			"net_quantity": 1,
			"pending_verification": false,
			"salvage_value": "0.0",
			"package_id": null,
			"checkout_on": null,
			"inventory_threshold": 0,
			"retire_reason": null,
			"retire_comments": null,
			"sub_group_id": null,
			"location_based_threshold": 0,
			"arbitration": 2,
			"rent_collected": "0.0",
			"tax_free": false,
			"sale_price": "0.0",
			"retired_by_id": null,
			"featured_item": false,
			"visible_on_web_store": false,
			"is_processed": false,
			"rental_meter": 0,
			"rental_meter_threshold": 0,
			"initial_stock_quantity": 0,
			"quickbooks_item_id": null,
			"sub_checked_out_to_id": null,
			"advanced_pricing": false,
			"bulk_import_id": null,
			"purchase_order_id": null,
			"available_for_sale": false,
			"checkout_via_bundle": false,
			"clone_from_asset_id": 2918095,
			"itam_hardware_id": null,
			"created_by_itam": false,
			"hidden_on_web_store": false,
			"last_checked_out_at": null,
			"last_checked_in_at": null,
			"last_assigned_to_id": null,
			"synced_with_jira_at": null,
			"sunshine_id": null,
			"retire_reason_id": null,
			"it_asset_source": null,
			"current_meter_reading": "0.0",
			"custom_substate_id": null,
			"merge_date": null,
			"candidate_email": null,
			"default_excess_location_threshold": 0,
			"average_cost_per_unit": "0.0",
			"usage_meter_threshold": null,
			"send_usage_meter_threshold_recurring_alert": false,
			"update_counter": 0,
			"network_asset": false,
			"group_rule_provisioned": false,
			"last_history_id": null,
			"qbd_item_name": null,
			"item_audit_id": null,
			"product_id": 41060,
			"product_identity": "remedyrgbw",
			"external_asset": false,
			"holder_id": null,
			"depreciation_calculation_required": false,
			"location_rule_provisioned": false,
			"latest_contract_id": null,
			"manufacturer": null,
			"assigned_to_user_name": null,
			"asset_type": "FixedAsset",
			"sub_checked_out_to_full_name": null,
			"active_sub_checkout": null,
			"location_number": 1,
			"group": {
				"depreciation_rates": [
					{
						"id": 2776,
						"group_id": 22999,
						"depreciation_method_id": 149,
						"rate": "20.0",
						"created_at": "2020-08-09 04:52:55",
						"updated_at": "2020-08-09 04:52:55",
						"useful_life": 12,
						"depreciation_method_name": "Straight Line"
					}
				]
			},
			"primary_user": null,
			"assigned_to_user_email": null,
			"display_image": "https://s3.amazonaws.com/docs.ezrentout.com/attachments/documents/1992990/original/Logo%28whiteexpanded%29blk.jpg?X-Amz-Algorithm=AWS4-HMAC-SHA256&X-Amz-Credential=AKIAVKFZ2DWIL7B6J3WK%2F20250717%2Fus-east-1%2Fs3%2Faws4_request&X-Amz-Date=20250717T205252Z&X-Amz-Expires=43200&X-Amz-SignedHeaders=host&X-Amz-Signature=6ce737a818b01acba16e861a19de6f3d7f0579f5ec0aed965e3c9053b078380c",
			"location_name": "DFW",
			"depreciated_value": {
				"straight_line": "$0.00"
			},
			"action": "create",
			"rental_prices": {
				"per_minute": "0.0",
				"hourly": "0.0",
				"daily": "0.0",
				"weekly": "55.9",
				"monthly": "0.0"
			}
		},
		{
			"name": "Remedy RGBW",
			"description": "RGBW LED battery, wireless DMX ",
			"price": "0.0",
			"identifier": "LED-R008",
			"vendor_id": null,
			"group_id": 22999,
			"created_at": "2023-06-12 14:06:14",
			"updated_at": "2023-06-21 11:07:02",
			"checkin_due_on": null,
			"audit_pending": false,
			"sequence_num": 639,
			"product_model_number": null,
			"documents_count": 1,
			"services_count": 0,
			"comments_count": 0,
			"state": "available",
			"purchased_on": "2017-12-02",
			"retired_on": null,
			"location_id": 12371,
			"net_quantity": 1,
			"pending_verification": false,
			"salvage_value": "0.0",
			"package_id": null,
			"checkout_on": null,
			"inventory_threshold": 0,
			"retire_reason": null,
			"retire_comments": null,
			"sub_group_id": null,
			"location_based_threshold": 0,
			"arbitration": 2,
			"rent_collected": "0.0",
			"tax_free": false,
			"sale_price": "0.0",
			"retired_by_id": null,
			"featured_item": false,
			"visible_on_web_store": false,
			"is_processed": false,
			"rental_meter": 0,
			"rental_meter_threshold": 0,
			"initial_stock_quantity": 0,
			"quickbooks_item_id": null,
			"sub_checked_out_to_id": null,
			"advanced_pricing": false,
			"bulk_import_id": null,
			"purchase_order_id": null,
			"available_for_sale": false,
			"checkout_via_bundle": false,
			"clone_from_asset_id": 2918095,
			"itam_hardware_id": null,
			"created_by_itam": false,
			"hidden_on_web_store": false,
			"last_checked_out_at": null,
			"last_checked_in_at": null,
			"last_assigned_to_id": null,
			"synced_with_jira_at": null,
			"sunshine_id": null,
			"retire_reason_id": null,
			"it_asset_source": null,
			"current_meter_reading": "0.0",
			"custom_substate_id": null,
			"merge_date": null,
			"candidate_email": null,
			"default_excess_location_threshold": 0,
			"average_cost_per_unit": "0.0",
			"usage_meter_threshold": null,
			"send_usage_meter_threshold_recurring_alert": false,
			"update_counter": 0,
			"network_asset": false,
			"group_rule_provisioned": false,
			"last_history_id": null,
			"qbd_item_name": null,
			"item_audit_id": null,
			"product_id": 41060,
			"product_identity": "remedyrgbw",
			"external_asset": false,
			"holder_id": null,
			"depreciation_calculation_required": false,
			"location_rule_provisioned": false,
			"latest_contract_id": null,
			"manufacturer": null,
			"assigned_to_user_name": null,
			"asset_type": "FixedAsset",
			"sub_checked_out_to_full_name": null,
			"active_sub_checkout": null,
			"location_number": 1,
			"group": {
				"depreciation_rates": [
					{
						"id": 2776,
						"group_id": 22999,
						"depreciation_method_id": 149,
						"rate": "20.0",
						"created_at": "2020-08-09 04:52:55",
						"updated_at": "2020-08-09 04:52:55",
						"useful_life": 12,
						"depreciation_method_name": "Straight Line"
					}
				]
			},
			"primary_user": null,
			"assigned_to_user_email": null,
			"display_image": "https://s3.amazonaws.com/docs.ezrentout.com/attachments/documents/1992990/original/Logo%28whiteexpanded%29blk.jpg?X-Amz-Algorithm=AWS4-HMAC-SHA256&X-Amz-Credential=AKIAVKFZ2DWIL7B6J3WK%2F20250717%2Fus-east-1%2Fs3%2Faws4_request&X-Amz-Date=20250717T205252Z&X-Amz-Expires=43200&X-Amz-SignedHeaders=host&X-Amz-Signature=6ce737a818b01acba16e861a19de6f3d7f0579f5ec0aed965e3c9053b078380c",
			"location_name": "DFW",
			"depreciated_value": {
				"straight_line": "$0.00"
			},
			"action": "create",
			"rental_prices": {
				"per_minute": "0.0",
				"hourly": "0.0",
				"daily": "0.0",
				"weekly": "55.9",
				"monthly": "0.0"
			}
		},
		{
			"name": "Remedy RGBW",
			"description": "RGBW LED battery, wireless DMX ",
			"price": "0.0",
			"identifier": "LED-R009",
			"vendor_id": null,
			"group_id": 22999,
			"created_at": "2023-06-12 14:06:14",
			"updated_at": "2023-06-21 11:07:07",
			"checkin_due_on": null,
			"audit_pending": false,
			"sequence_num": 640,
			"product_model_number": null,
			"documents_count": 1,
			"services_count": 0,
			"comments_count": 0,
			"state": "available",
			"purchased_on": "2017-12-02",
			"retired_on": null,
			"location_id": 12371,
			"net_quantity": 1,
			"pending_verification": false,
			"salvage_value": "0.0",
			"package_id": null,
			"checkout_on": null,
			"inventory_threshold": 0,
			"retire_reason": null,
			"retire_comments": null,
			"sub_group_id": null,
			"location_based_threshold": 0,
			"arbitration": 2,
			"rent_collected": "0.0",
			"tax_free": false,
			"sale_price": "0.0",
			"retired_by_id": null,
			"featured_item": false,
			"visible_on_web_store": false,
			"is_processed": false,
			"rental_meter": 0,
			"rental_meter_threshold": 0,
			"initial_stock_quantity": 0,
			"quickbooks_item_id": null,
			"sub_checked_out_to_id": null,
			"advanced_pricing": false,
			"bulk_import_id": null,
			"purchase_order_id": null,
			"available_for_sale": false,
			"checkout_via_bundle": false,
			"clone_from_asset_id": 2918095,
			"itam_hardware_id": null,
			"created_by_itam": false,
			"hidden_on_web_store": false,
			"last_checked_out_at": null,
			"last_checked_in_at": null,
			"last_assigned_to_id": null,
			"synced_with_jira_at": null,
			"sunshine_id": null,
			"retire_reason_id": null,
			"it_asset_source": null,
			"current_meter_reading": "0.0",
			"custom_substate_id": null,
			"merge_date": null,
			"candidate_email": null,
			"default_excess_location_threshold": 0,
			"average_cost_per_unit": "0.0",
			"usage_meter_threshold": null,
			"send_usage_meter_threshold_recurring_alert": false,
			"update_counter": 0,
			"network_asset": false,
			"group_rule_provisioned": false,
			"last_history_id": null,
			"qbd_item_name": null,
			"item_audit_id": null,
			"product_id": 41060,
			"product_identity": "remedyrgbw",
			"external_asset": false,
			"holder_id": null,
			"depreciation_calculation_required": false,
			"location_rule_provisioned": false,
			"latest_contract_id": null,
			"manufacturer": null,
			"assigned_to_user_name": null,
			"asset_type": "FixedAsset",
			"sub_checked_out_to_full_name": null,
			"active_sub_checkout": null,
			"location_number": 1,
			"group": {
				"depreciation_rates": [
					{
						"id": 2776,
						"group_id": 22999,
						"depreciation_method_id": 149,
						"rate": "20.0",
						"created_at": "2020-08-09 04:52:55",
						"updated_at": "2020-08-09 04:52:55",
						"useful_life": 12,
						"depreciation_method_name": "Straight Line"
					}
				]
			},
			"primary_user": null,
			"assigned_to_user_email": null,
			"display_image": "https://s3.amazonaws.com/docs.ezrentout.com/attachments/documents/1992990/original/Logo%28whiteexpanded%29blk.jpg?X-Amz-Algorithm=AWS4-HMAC-SHA256&X-Amz-Credential=AKIAVKFZ2DWIL7B6J3WK%2F20250717%2Fus-east-1%2Fs3%2Faws4_request&X-Amz-Date=20250717T205252Z&X-Amz-Expires=43200&X-Amz-SignedHeaders=host&X-Amz-Signature=6ce737a818b01acba16e861a19de6f3d7f0579f5ec0aed965e3c9053b078380c",
			"location_name": "DFW",
			"depreciated_value": {
				"straight_line": "$0.00"
			},
			"action": "create",
			"rental_prices": {
				"per_minute": "0.0",
				"hourly": "0.0",
				"daily": "0.0",
				"weekly": "55.9",
				"monthly": "0.0"
			}
		},
		{
			"name": "Remedy RGBW",
			"description": "RGBW LED battery, wireless DMX ",
			"price": "0.0",
			"identifier": "LED-R010",
			"vendor_id": null,
			"group_id": 22999,
			"created_at": "2023-07-18 17:55:25",
			"updated_at": "2024-02-12 14:53:23",
			"checkin_due_on": null,
			"audit_pending": false,
			"sequence_num": 737,
			"product_model_number": null,
			"documents_count": 1,
			"services_count": 0,
			"comments_count": 0,
			"state": "available",
			"purchased_on": "2017-12-02",
			"retired_on": null,
			"location_id": 12371,
			"net_quantity": 1,
			"pending_verification": false,
			"salvage_value": "0.0",
			"package_id": null,
			"checkout_on": null,
			"inventory_threshold": 0,
			"retire_reason": null,
			"retire_comments": null,
			"sub_group_id": null,
			"location_based_threshold": 0,
			"arbitration": 2,
			"rent_collected": "55.9",
			"tax_free": false,
			"sale_price": "0.0",
			"retired_by_id": null,
			"featured_item": false,
			"visible_on_web_store": false,
			"is_processed": false,
			"rental_meter": 0,
			"rental_meter_threshold": 0,
			"initial_stock_quantity": 0,
			"quickbooks_item_id": null,
			"sub_checked_out_to_id": null,
			"advanced_pricing": false,
			"bulk_import_id": null,
			"purchase_order_id": null,
			"available_for_sale": false,
			"checkout_via_bundle": false,
			"clone_from_asset_id": 2918105,
			"itam_hardware_id": null,
			"created_by_itam": false,
			"hidden_on_web_store": false,
			"last_checked_out_at": "2024-02-09 13:51:00",
			"last_checked_in_at": null,
			"last_assigned_to_id": 21718,
			"synced_with_jira_at": null,
			"sunshine_id": null,
			"retire_reason_id": null,
			"it_asset_source": null,
			"current_meter_reading": "0.0",
			"custom_substate_id": null,
			"merge_date": null,
			"candidate_email": null,
			"default_excess_location_threshold": 0,
			"average_cost_per_unit": "0.0",
			"usage_meter_threshold": null,
			"send_usage_meter_threshold_recurring_alert": false,
			"update_counter": 0,
			"network_asset": false,
			"group_rule_provisioned": false,
			"last_history_id": 9476037,
			"qbd_item_name": null,
			"item_audit_id": null,
			"product_id": 41060,
			"product_identity": "remedyrgbw",
			"external_asset": false,
			"holder_id": null,
			"depreciation_calculation_required": false,
			"location_rule_provisioned": false,
			"latest_contract_id": null,
			"manufacturer": null,
			"assigned_to_user_name": null,
			"asset_type": "FixedAsset",
			"sub_checked_out_to_full_name": null,
			"active_sub_checkout": null,
			"location_number": 1,
			"group": {
				"depreciation_rates": [
					{
						"id": 2776,
						"group_id": 22999,
						"depreciation_method_id": 149,
						"rate": "20.0",
						"created_at": "2020-08-09 04:52:55",
						"updated_at": "2020-08-09 04:52:55",
						"useful_life": 12,
						"depreciation_method_name": "Straight Line"
					}
				]
			},
			"primary_user": null,
			"assigned_to_user_email": null,
			"display_image": "https://s3.amazonaws.com/docs.ezrentout.com/attachments/documents/1992990/original/Logo%28whiteexpanded%29blk.jpg?X-Amz-Algorithm=AWS4-HMAC-SHA256&X-Amz-Credential=AKIAVKFZ2DWIL7B6J3WK%2F20250717%2Fus-east-1%2Fs3%2Faws4_request&X-Amz-Date=20250717T205252Z&X-Amz-Expires=43200&X-Amz-SignedHeaders=host&X-Amz-Signature=6ce737a818b01acba16e861a19de6f3d7f0579f5ec0aed965e3c9053b078380c",
			"location_name": "DFW",
			"depreciated_value": {
				"straight_line": "$0.00"
			},
			"action": "create",
			"rental_prices": {
				"per_minute": "0.0",
				"hourly": "0.0",
				"daily": "0.0",
				"weekly": "55.9",
				"monthly": "0.0"
			}
		},
		{
			"name": "SCOUT-25",
			"description": "LED Par 46 RGBW",
			"price": "140.0",
			"identifier": "SCOUT-001",
			"vendor_id": 9656,
			"group_id": 22999,
			"created_at": "2019-02-06 14:36:34",
			"updated_at": "2025-04-28 08:51:23",
			"checkin_due_on": null,
			"audit_pending": false,
			"sequence_num": 216,
			"product_model_number": "4in1X6",
			"documents_count": 1,
			"services_count": 0,
			"comments_count": 1,
			"state": "available",
			"purchased_on": "2016-01-03",
			"retired_on": null,
			"location_id": 12371,
			"net_quantity": 1,
			"pending_verification": false,
			"salvage_value": "0.0",
			"package_id": null,
			"checkout_on": null,
			"inventory_threshold": 0,
			"retire_reason": null,
			"retire_comments": null,
			"sub_group_id": null,
			"location_based_threshold": 0,
			"arbitration": 2,
			"rent_collected": "1209.5",
			"tax_free": false,
			"sale_price": "0.0",
			"retired_by_id": null,
			"featured_item": false,
			"visible_on_web_store": false,
			"is_processed": false,
			"rental_meter": 0,
			"rental_meter_threshold": 0,
			"initial_stock_quantity": 0,
			"quickbooks_item_id": null,
			"sub_checked_out_to_id": null,
			"advanced_pricing": false,
			"bulk_import_id": null,
			"purchase_order_id": null,
			"available_for_sale": false,
			"checkout_via_bundle": false,
			"clone_from_asset_id": 1105148,
			"itam_hardware_id": null,
			"created_by_itam": false,
			"hidden_on_web_store": false,
			"last_checked_out_at": "2025-04-21 09:58:29",
			"last_checked_in_at": "2024-05-20 11:01:18",
			"last_assigned_to_id": 282746,
			"synced_with_jira_at": null,
			"sunshine_id": null,
			"retire_reason_id": null,
			"it_asset_source": null,
			"current_meter_reading": "0.0",
			"custom_substate_id": null,
			"merge_date": null,
			"candidate_email": null,
			"default_excess_location_threshold": 0,
			"average_cost_per_unit": "0.0",
			"usage_meter_threshold": null,
			"send_usage_meter_threshold_recurring_alert": false,
			"update_counter": 0,
			"network_asset": false,
			"group_rule_provisioned": false,
			"last_history_id": 11436398,
			"qbd_item_name": null,
			"item_audit_id": null,
			"product_id": 41025,
			"product_identity": "scout25",
			"external_asset": false,
			"holder_id": null,
			"depreciation_calculation_required": false,
			"location_rule_provisioned": false,
			"latest_contract_id": null,
			"manufacturer": null,
			"assigned_to_user_name": null,
			"asset_type": "FixedAsset",
			"sub_checked_out_to_full_name": null,
			"active_sub_checkout": null,
			"location_number": 1,
			"group": {
				"depreciation_rates": [
					{
						"id": 2776,
						"group_id": 22999,
						"depreciation_method_id": 149,
						"rate": "20.0",
						"created_at": "2020-08-09 04:52:55",
						"updated_at": "2020-08-09 04:52:55",
						"useful_life": 12,
						"depreciation_method_name": "Straight Line"
					}
				]
			},
			"primary_user": null,
			"assigned_to_user_email": null,
			"display_image": "https://s3.amazonaws.com/docs.ezrentout.com/attachments/documents/311420/original/Scout.jpg?X-Amz-Algorithm=AWS4-HMAC-SHA256&X-Amz-Credential=AKIAVKFZ2DWIL7B6J3WK%2F20250717%2Fus-east-1%2Fs3%2Faws4_request&X-Amz-Date=20250717T205252Z&X-Amz-Expires=43200&X-Amz-SignedHeaders=host&X-Amz-Signature=09bf7f33e0c858d259920dfdedccb68995c7417870a0009afc15ffc8f55a506c",
			"location_name": "DFW",
			"depreciated_value": {
				"straight_line": "$0.00"
			},
			"action": "create",
			"rental_prices": {
				"per_minute": "0.0",
				"hourly": "0.0",
				"daily": "0.0",
				"weekly": "41.0",
				"monthly": "0.0"
			}
		},
		{
			"name": "SCOUT-25",
			"description": "LED Par 46 RGBW",
			"price": "140.0",
			"identifier": "SCOUT-002",
			"vendor_id": 9656,
			"group_id": 22999,
			"created_at": "2019-02-06 14:36:34",
			"updated_at": "2025-04-28 08:51:23",
			"checkin_due_on": null,
			"audit_pending": false,
			"sequence_num": 217,
			"product_model_number": "4in1X6 ",
			"documents_count": 1,
			"services_count": 0,
			"comments_count": 1,
			"state": "available",
			"purchased_on": "2016-01-03",
			"retired_on": null,
			"location_id": 12371,
			"net_quantity": 1,
			"pending_verification": false,
			"salvage_value": "0.0",
			"package_id": null,
			"checkout_on": null,
			"inventory_threshold": 0,
			"retire_reason": null,
			"retire_comments": null,
			"sub_group_id": null,
			"location_based_threshold": 0,
			"arbitration": 2,
			"rent_collected": "1168.5",
			"tax_free": false,
			"sale_price": "0.0",
			"retired_by_id": null,
			"featured_item": false,
			"visible_on_web_store": false,
			"is_processed": false,
			"rental_meter": 0,
			"rental_meter_threshold": 0,
			"initial_stock_quantity": 0,
			"quickbooks_item_id": null,
			"sub_checked_out_to_id": null,
			"advanced_pricing": false,
			"bulk_import_id": null,
			"purchase_order_id": null,
			"available_for_sale": false,
			"checkout_via_bundle": false,
			"clone_from_asset_id": 1105148,
			"itam_hardware_id": null,
			"created_by_itam": false,
			"hidden_on_web_store": false,
			"last_checked_out_at": "2025-04-21 09:58:29",
			"last_checked_in_at": "2024-05-20 11:01:18",
			"last_assigned_to_id": 282746,
			"synced_with_jira_at": null,
			"sunshine_id": null,
			"retire_reason_id": null,
			"it_asset_source": null,
			"current_meter_reading": "0.0",
			"custom_substate_id": null,
			"merge_date": null,
			"candidate_email": null,
			"default_excess_location_threshold": 0,
			"average_cost_per_unit": "0.0",
			"usage_meter_threshold": null,
			"send_usage_meter_threshold_recurring_alert": false,
			"update_counter": 0,
			"network_asset": false,
			"group_rule_provisioned": false,
			"last_history_id": 11436400,
			"qbd_item_name": null,
			"item_audit_id": null,
			"product_id": 41025,
			"product_identity": "scout25",
			"external_asset": false,
			"holder_id": null,
			"depreciation_calculation_required": false,
			"location_rule_provisioned": false,
			"latest_contract_id": null,
			"manufacturer": null,
			"assigned_to_user_name": null,
			"asset_type": "FixedAsset",
			"sub_checked_out_to_full_name": null,
			"active_sub_checkout": null,
			"location_number": 1,
			"group": {
				"depreciation_rates": [
					{
						"id": 2776,
						"group_id": 22999,
						"depreciation_method_id": 149,
						"rate": "20.0",
						"created_at": "2020-08-09 04:52:55",
						"updated_at": "2020-08-09 04:52:55",
						"useful_life": 12,
						"depreciation_method_name": "Straight Line"
					}
				]
			},
			"primary_user": null,
			"assigned_to_user_email": null,
			"display_image": "https://s3.amazonaws.com/docs.ezrentout.com/attachments/documents/311420/original/Scout.jpg?X-Amz-Algorithm=AWS4-HMAC-SHA256&X-Amz-Credential=AKIAVKFZ2DWIL7B6J3WK%2F20250717%2Fus-east-1%2Fs3%2Faws4_request&X-Amz-Date=20250717T205252Z&X-Amz-Expires=43200&X-Amz-SignedHeaders=host&X-Amz-Signature=09bf7f33e0c858d259920dfdedccb68995c7417870a0009afc15ffc8f55a506c",
			"location_name": "DFW",
			"depreciated_value": {
				"straight_line": "$0.00"
			},
			"action": "create",
			"rental_prices": {
				"per_minute": "0.0",
				"hourly": "0.0",
				"daily": "0.0",
				"weekly": "41.0",
				"monthly": "0.0"
			}
		},
		{
			"name": "SCOUT-25",
			"description": "LED Par 46 RGBW",
			"price": "140.0",
			"identifier": "SCOUT-003",
			"vendor_id": 9656,
			"group_id": 22999,
			"created_at": "2019-02-06 14:36:34",
			"updated_at": "2025-04-28 08:51:23",
			"checkin_due_on": null,
			"audit_pending": false,
			"sequence_num": 218,
			"product_model_number": "4in1X6 ",
			"documents_count": 1,
			"services_count": 0,
			"comments_count": 1,
			"state": "available",
			"purchased_on": "2016-01-03",
			"retired_on": null,
			"location_id": 12371,
			"net_quantity": 1,
			"pending_verification": false,
			"salvage_value": "0.0",
			"package_id": null,
			"checkout_on": null,
			"inventory_threshold": 0,
			"retire_reason": null,
			"retire_comments": null,
			"sub_group_id": null,
			"location_based_threshold": 0,
			"arbitration": 2,
			"rent_collected": "1127.5",
			"tax_free": false,
			"sale_price": "0.0",
			"retired_by_id": null,
			"featured_item": false,
			"visible_on_web_store": false,
			"is_processed": false,
			"rental_meter": 0,
			"rental_meter_threshold": 0,
			"initial_stock_quantity": 0,
			"quickbooks_item_id": null,
			"sub_checked_out_to_id": null,
			"advanced_pricing": false,
			"bulk_import_id": null,
			"purchase_order_id": null,
			"available_for_sale": false,
			"checkout_via_bundle": false,
			"clone_from_asset_id": 1105148,
			"itam_hardware_id": null,
			"created_by_itam": false,
			"hidden_on_web_store": false,
			"last_checked_out_at": "2025-04-21 09:58:29",
			"last_checked_in_at": "2024-04-22 11:50:55",
			"last_assigned_to_id": 282746,
			"synced_with_jira_at": null,
			"sunshine_id": null,
			"retire_reason_id": null,
			"it_asset_source": null,
			"current_meter_reading": "0.0",
			"custom_substate_id": null,
			"merge_date": null,
			"candidate_email": null,
			"default_excess_location_threshold": 0,
			"average_cost_per_unit": "0.0",
			"usage_meter_threshold": null,
			"send_usage_meter_threshold_recurring_alert": false,
			"update_counter": 0,
			"network_asset": false,
			"group_rule_provisioned": false,
			"last_history_id": 11436401,
			"qbd_item_name": null,
			"item_audit_id": null,
			"product_id": 41025,
			"product_identity": "scout25",
			"external_asset": false,
			"holder_id": null,
			"depreciation_calculation_required": false,
			"location_rule_provisioned": false,
			"latest_contract_id": null,
			"manufacturer": null,
			"assigned_to_user_name": null,
			"asset_type": "FixedAsset",
			"sub_checked_out_to_full_name": null,
			"active_sub_checkout": null,
			"location_number": 1,
			"group": {
				"depreciation_rates": [
					{
						"id": 2776,
						"group_id": 22999,
						"depreciation_method_id": 149,
						"rate": "20.0",
						"created_at": "2020-08-09 04:52:55",
						"updated_at": "2020-08-09 04:52:55",
						"useful_life": 12,
						"depreciation_method_name": "Straight Line"
					}
				]
			},
			"primary_user": null,
			"assigned_to_user_email": null,
			"display_image": "https://s3.amazonaws.com/docs.ezrentout.com/attachments/documents/311420/original/Scout.jpg?X-Amz-Algorithm=AWS4-HMAC-SHA256&X-Amz-Credential=AKIAVKFZ2DWIL7B6J3WK%2F20250717%2Fus-east-1%2Fs3%2Faws4_request&X-Amz-Date=20250717T205252Z&X-Amz-Expires=43200&X-Amz-SignedHeaders=host&X-Amz-Signature=09bf7f33e0c858d259920dfdedccb68995c7417870a0009afc15ffc8f55a506c",
			"location_name": "DFW",
			"depreciated_value": {
				"straight_line": "$0.00"
			},
			"action": "create",
			"rental_prices": {
				"per_minute": "0.0",
				"hourly": "0.0",
				"daily": "0.0",
				"weekly": "41.0",
				"monthly": "0.0"
			}
		}
	],
	"total_pages": 20
}